{
    "variants": {
        "age=0": { "model": "zanextras:greenbean_stage_0" },
        "age=1": { "model": "zanextras:greenbean_stage_1" },
        "age=2": { "model": "zanextras:greenbean_stage_2" },
        "age=3": { "model": "zanextras:greenbean_stage_3" },
        "age=4": { "model": "zanextras:greenbean_stage_4" },
        "age=5": { "model": "zanextras:greenbean_stage_5" },
        "age=6": { "model": "zanextras:greenbean_stage_6" },
        "age=7": { "model": "zanextras:greenbean_stage_7" }
    }
}
